typycheck-0.0.1.dist-info/METADATA
typycheck-0.0.1.dist-info/WHEEL
typycheck-0.0.1.dist-info/entry_points.txt
typycheck/__init__.py
typycheck/main.py
typycheck/rust.pypy38-pp73-x86-linux-gnu.so
typycheck-0.0.1.dist-info/RECORD
